easybox
