Metadata-Version: 1.0
Name: easybox
Version: 0.0.3
Summary: A simple but powerful bounding box annotation tool by Python
Home-page: https://github.com/vra/easybox
Author: Yunfeng Wang
Author-email: wyf.brz@gmail.com
License: MIT Licence
Keywords: easybox,Detection,Python,Deep-learning,TKinter
Platform: any
